{
  "US": 20,
  "IS": 24,
  "LU": 22,
  "QA": 19,
  "CA": 18,
  "UK": 16,
  "AU": 17.5,
  "DE": 14,
  "CH": 21,
  "NL": 13.5,
  "SE": 13,
  "NO": 14.5,
  "DK": 13,
  "FR": 12,
  "ES": 10,
  "IT": 10.5,
  "BE": 11.5,
  "AT": 12.5,
  "IE": 15.5,
  "NZ": 14,
  "SG": 17,
  "JP": 11,
  "KR": 9.5,
  "AE": 18.5,
  "SA": 9,
  "IL": 10.5,
  "PL": 7.5,
  "CZ": 7,
  "PT": 8,
  "GR": 7,
  "HU": 6.5,
  "RO": 6,
  "BG": 5.5,
  "HR": 6.5,
  "SI": 7.5,
  "EE": 7,
  "LT": 6.5,
  "LV": 6,
  "SK": 6.5,
  "MX": 5,
  "BR": 4.2,
  "AR": 4.5,
  "CL": 6,
  "CO": 4,
  "PE": 4.5,
  "VE": 3,
  "EC": 3.5,
  "UY": 5.5,
  "CR": 5,
  "PA": 4.5,
  "IN": 2.1,
  "ID": 4,
  "TH": 4.5,
  "VN": 3,
  "PH": 3.5,
  "MY": 5,
  "PK": 2.5,
  "BD": 2,
  "LK": 2.5,
  "MM": 2,
  "KH": 2.5,
  "CN": 6,
  "TW": 8,
  "HK": 9.5,
  "ZA": 8,
  "NG": 3.4,
  "KE": 3,
  "EG": 3.5,
  "MA": 4,
  "GH": 2.5,
  "TZ": 2,
  "UG": 2,
  "ET": 1.5,
  "DZ": 3,
  "TN": 3.5,
  "TR": 6.5,
  "RU": 5,
  "UA": 4,
  "BY": 3.5,
  "KZ": 4,
  "UZ": 2.5,
  "GE": 4.5,
  "AM": 4,
  "AZ": 4.5
}
